pandora/__init__.py
pandora/abs2rel.py
pandora/check_phred.py
pandora/extract_seq.py
pandora/fq2fa.py
pandora/fxlength.py
pandora/readseq.py
pandora/summary_mag.py
pandora/version.py
pandora_microbiome-0.2.0.data/scripts/pandora
pandora_microbiome-0.2.0.dist-info/METADATA
pandora_microbiome-0.2.0.dist-info/WHEEL
pandora_microbiome-0.2.0.dist-info/top_level.txt
pandora_microbiome-0.2.0.dist-info/RECORD
